iobio/__init__.py
iobio/entropy/__init__.py
iobio/explicitsemanticanalysis/__init__.py
iobio/qnorm/__init__.py
iobio-0.1.0.dist-info/DESCRIPTION.rst
iobio-0.1.0.dist-info/METADATA
iobio-0.1.0.dist-info/RECORD
iobio-0.1.0.dist-info/WHEEL
iobio-0.1.0.dist-info/metadata.json
iobio-0.1.0.dist-info/top_level.txt
